<annotation>
	<folder>images</folder>
	<filename>obstacle107.jpg</filename>
	<path>C:\Users\geepe\Desktop\Learning Materials\4th year 2nd\ISDP2\Khai's img\images\obstacle107.jpg</path>
	<source>
		<database>Unknown</database>
	</source>
	<size>
		<width>640</width>
		<height>480</height>
		<depth>3</depth>
	</size>
	<segmented>0</segmented>
	<object>
		<name>obstacle</name>
		<pose>Unspecified</pose>
		<truncated>1</truncated>
		<difficult>0</difficult>
		<bndbox>
			<xmin>1</xmin>
			<ymin>351</ymin>
			<xmax>17</xmax>
			<ymax>395</ymax>
		</bndbox>
	</object>
</annotation>
